odoo8_addon_account_balance_line-8.0.1.1.1.99.dev16-py2.7-nspkg.pth
odoo8_addon_account_balance_line-8.0.1.1.1.99.dev16.dist-info/DESCRIPTION.rst
odoo8_addon_account_balance_line-8.0.1.1.1.99.dev16.dist-info/METADATA
odoo8_addon_account_balance_line-8.0.1.1.1.99.dev16.dist-info/RECORD
odoo8_addon_account_balance_line-8.0.1.1.1.99.dev16.dist-info/WHEEL
odoo8_addon_account_balance_line-8.0.1.1.1.99.dev16.dist-info/metadata.json
odoo8_addon_account_balance_line-8.0.1.1.1.99.dev16.dist-info/namespace_packages.txt
odoo8_addon_account_balance_line-8.0.1.1.1.99.dev16.dist-info/top_level.txt
odoo_addons/account_balance_line/README.rst
odoo_addons/account_balance_line/__init__.py
odoo_addons/account_balance_line/__openerp__.py
odoo_addons/account_balance_line/account_move_line.py
odoo_addons/account_balance_line/account_move_line_view.xml
odoo_addons/account_balance_line/i18n/account_balance_line.pot
odoo_addons/account_balance_line/i18n/ar.po
odoo_addons/account_balance_line/i18n/bs.po
odoo_addons/account_balance_line/i18n/ca.po
odoo_addons/account_balance_line/i18n/cs.po
odoo_addons/account_balance_line/i18n/de.po
odoo_addons/account_balance_line/i18n/en_GB.po
odoo_addons/account_balance_line/i18n/es.po
odoo_addons/account_balance_line/i18n/es_CR.po
odoo_addons/account_balance_line/i18n/es_EC.po
odoo_addons/account_balance_line/i18n/es_MX.po
odoo_addons/account_balance_line/i18n/fr.po
odoo_addons/account_balance_line/i18n/gl.po
odoo_addons/account_balance_line/i18n/hr.po
odoo_addons/account_balance_line/i18n/hu.po
odoo_addons/account_balance_line/i18n/id.po
odoo_addons/account_balance_line/i18n/it.po
odoo_addons/account_balance_line/i18n/ja.po
odoo_addons/account_balance_line/i18n/lt.po
odoo_addons/account_balance_line/i18n/mk.po
odoo_addons/account_balance_line/i18n/mn.po
odoo_addons/account_balance_line/i18n/nb.po
odoo_addons/account_balance_line/i18n/nl.po
odoo_addons/account_balance_line/i18n/nl_BE.po
odoo_addons/account_balance_line/i18n/pt.po
odoo_addons/account_balance_line/i18n/pt_BR.po
odoo_addons/account_balance_line/i18n/pt_PT.po
odoo_addons/account_balance_line/i18n/ro.po
odoo_addons/account_balance_line/i18n/ro_RO.po
odoo_addons/account_balance_line/i18n/ru.po
odoo_addons/account_balance_line/i18n/sl.po
odoo_addons/account_balance_line/i18n/sv.po
odoo_addons/account_balance_line/i18n/tr.po
odoo_addons/account_balance_line/i18n/zh_CN.po
odoo_addons/account_balance_line/i18n/zh_TW.po
